forecast/__init__.py
forecast/service.py
forecast/bias/__init__.py
forecast/bias/bias.py
forecast/commit/__init__.py
forecast/commit/capacity.py
forecast/core/__init__.py
forecast/core/types.py
forecast/correction/__init__.py
forecast/correction/correction.py
forecast/inflation/__init__.py
forecast/inflation/inflation.py
forecast/pert/__init__.py
forecast/pert/pert.py
forecast/utils/__init__.py
forecast/utils/stats.py
forecast_pert-0.3.5.dist-info/licenses/LICENSE
forecast_pert-0.3.5.dist-info/METADATA
forecast_pert-0.3.5.dist-info/WHEEL
forecast_pert-0.3.5.dist-info/top_level.txt
forecast_pert-0.3.5.dist-info/RECORD
