Metadata-Version: 2.4
Name: forecast-pert
Version: 0.3.5
Summary: Calibrated three-point (PERT) distributions with empirical-Bayes bias correction
Author-email: Emmett Miller <emmett.miller7@outlook.com>
License: MIT License
Keywords: PERT,forecasting,agile,bias,empirical-bayes,calibration
Requires-Python: >=3.9
License-File: LICENSE
Provides-Extra: dev
Requires-Dist: pytest>=8.0; extra == "dev"
Requires-Dist: pylint>=2.17; extra == "dev"
Requires-Dist: ruff>=0.6; extra == "dev"
Requires-Dist: isort>=5.13; extra == "dev"
Dynamic: license-file
